MANIFEST.in
README.markdown
setup.py
django_extensible_profiles.egg-info/PKG-INFO
django_extensible_profiles.egg-info/SOURCES.txt
django_extensible_profiles.egg-info/dependency_links.txt
django_extensible_profiles.egg-info/top_level.txt
profiles/__init__.py
profiles/admin.py
profiles/forms.py
profiles/models.py
profiles/signals.py
profiles/tests.py
profiles/unique_id.py
profiles/urls.py
profiles/utils.py
profiles/views.py
profiles/extensions/__init__.py
profiles/extensions/address.py
profiles/extensions/modified.py
profiles/extensions/permissions.py
profiles/extensions/picture.py
profiles/extensions/title.py
profiles/management/__init__.py
profiles/management/commands/__init__.py
profiles/management/commands/add_user_profile.py
profiles/modules/__init__.py
profiles/modules/addresses/__init__.py
profiles/modules/addresses/admin.py
profiles/modules/addresses/models.py
profiles/modules/addresses/extensions/__init__.py
profiles/modules/addresses/extensions/addresses.py
profiles/modules/codes/__init__.py
profiles/modules/codes/admin.py
profiles/modules/codes/fields.py
profiles/modules/codes/models.py
profiles/modules/codes/extensions/__init__.py
profiles/modules/codes/extensions/codes.py
profiles/modules/codes/templates/admin/profiles/code/change_list.html
profiles/modules/notifications/__init__.py
profiles/modules/notifications/admin.py
profiles/modules/notifications/models.py
profiles/modules/notifications/extensions/__init__.py
profiles/modules/notifications/extensions/notifications.py
profiles/modules/options/__init__.py
profiles/modules/options/admin.py
profiles/modules/options/models.py
profiles/modules/options/extensions/__init__.py
profiles/modules/options/extensions/options.py
profiles/templates/profiles/_profile_menu.html
profiles/templates/profiles/_users_count.html
profiles/templates/profiles/profile.html
profiles/templates/profiles/profile_base.html
profiles/templates/profiles/profile_form.html
profiles/templates/registration/password_change_done.html
profiles/templates/registration/password_change_form.html
profiles/templatetags/__init__.py
profiles/templatetags/profile_tags.py