Metadata-Version: 1.0
Name: django-extensible-profiles
Version: 1.3.6
Summary: Generic extensible django user profiles.
Home-page: http://incuna.com/
Author: Incuna Ltd
Author-email: admin@incuna.com
License: UNKNOWN
Platform: UNKNOWN
